MANIFEST.in
setup.py
biojulia/404.html
biojulia/__init__.py
biojulia/base.html
biojulia/content.html
biojulia/nav-sub.html
biojulia/nav.html
biojulia/toc.html
biojulia/css/base.css
biojulia/css/biojulia.css
biojulia/css/bootstrap-custom.css
biojulia/css/bootstrap-custom.min.css
biojulia/css/font-awesome-4.0.3.css
biojulia/css/friendly.css
biojulia/css/highlight.css
biojulia/fonts/fontawesome-webfont.eot
biojulia/fonts/fontawesome-webfont.svg
biojulia/fonts/fontawesome-webfont.ttf
biojulia/fonts/fontawesome-webfont.woff
biojulia/img/favicon.ico
biojulia/img/grid1.png
biojulia/img/grid10.png
biojulia/img/grid11.png
biojulia/img/grid12.png
biojulia/img/grid13.png
biojulia/img/grid14.png
biojulia/img/grid15.png
biojulia/img/grid16.png
biojulia/img/grid17.png
biojulia/img/grid18.png
biojulia/img/grid19.png
biojulia/img/grid2.png
biojulia/img/grid20.png
biojulia/img/grid3.png
biojulia/img/grid4.png
biojulia/img/grid5.png
biojulia/img/grid6.png
biojulia/img/grid7.png
biojulia/img/grid8.png
biojulia/img/grid9.png
biojulia/js/base.js
biojulia/js/bootstrap-3.0.3.min.js
biojulia/js/highlight.pack.js
biojulia/js/jquery-1.10.2.min.js
mkdocs_biojulia.egg-info/PKG-INFO
mkdocs_biojulia.egg-info/SOURCES.txt
mkdocs_biojulia.egg-info/dependency_links.txt
mkdocs_biojulia.egg-info/entry_points.txt
mkdocs_biojulia.egg-info/not-zip-safe
mkdocs_biojulia.egg-info/top_level.txt