Metadata-Version: 1.0
Name: mkdocs-biojulia
Version: 1.0.1
Summary: Mkdocs Cinder theme customised for BioJulia.
Home-page: https://github.com/BioJulia/mkdocs-biojulia
Author: The BioJulia Organisation
Author-email: Ward9250@gmail.com
License: MIT
Platform: UNKNOWN
